zipjson/__init__.py
zipjson-0.0.1.dist-info/LICENSE
zipjson-0.0.1.dist-info/METADATA
zipjson-0.0.1.dist-info/WHEEL
zipjson-0.0.1.dist-info/top_level.txt
zipjson-0.0.1.dist-info/RECORD
