Metadata-Version: 2.1
Name: zipjson
Version: 0.0.1
Summary: A tool to create and read compressed JSON files
Home-page: https://github.com/vguzov/zipjson
Author: Vladimir Guzov
Author-email: guzov.mail@gmail.com
License: UNKNOWN
Keywords: json,zip
Platform: UNKNOWN
Classifier: Intended Audience :: Developers
Classifier: License :: OSI Approved :: MIT License
Classifier: Natural Language :: English
Classifier: Operating System :: OS Independent
Classifier: Programming Language :: Python
Classifier: Programming Language :: Python :: 3
